nacos/__init__.py
nacos/errors.py
nacos/models.py
nacos/utils.py
nacos/api/__init__.py
nacos/api/base.py
nacos/api/config.py
nacos/api/instance.py
nacos/api/models.py
nacos/api/service.py
nacos/client/__init__.py
nacos/client/base.py
nacos_client_py-0.0.17.dist-info/LICENSE
nacos_client_py-0.0.17.dist-info/METADATA
nacos_client_py-0.0.17.dist-info/WHEEL
nacos_client_py-0.0.17.dist-info/top_level.txt
nacos_client_py-0.0.17.dist-info/RECORD
