Metadata-Version: 2.1
Name: nacos-client-py
Version: 0.0.17
Summary: Python client for Nacos
Home-page: UNKNOWN
Author: rencanwei
Author-email: rencanwei@58.com
License: Apache License 2.0
Keywords: nacos-client-py
Platform: UNKNOWN
Classifier: Topic :: Software Development :: Libraries :: Python Modules
Classifier: Operating System :: OS Independent
Classifier: Programming Language :: Python :: 3.6
Classifier: Programming Language :: Python :: 3.7
Classifier: Programming Language :: Python :: 3.8
Classifier: Programming Language :: Python :: 3.9
Requires-Python: >=3.6
License-File: LICENSE
Requires-Dist: orjson (>=3.8.7)
Requires-Dist: httpx (>=0.23.3)
Requires-Dist: pydantic[dotenv] (>=1.10.6)
Requires-Dist: typing-extensions (>=4.5.0)
